CHANGES.txt
LICENSE.GPL
README.txt
setup.py
docs/LICENSE.GPL
docs/LICENSE.txt
plone/__init__.py
plone.app.relations.egg-info/PKG-INFO
plone.app.relations.egg-info/SOURCES.txt
plone.app.relations.egg-info/dependency_links.txt
plone.app.relations.egg-info/entry_points.txt
plone.app.relations.egg-info/namespace_packages.txt
plone.app.relations.egg-info/not-zip-safe
plone.app.relations.egg-info/requires.txt
plone.app.relations.egg-info/top_level.txt
plone/app/__init__.py
plone/app/relations/AddLocalRoleManagerForm.pt
plone/app/relations/README.txt
plone/app/relations/__init__.py
plone/app/relations/annotations.py
plone/app/relations/configure.zcml
plone/app/relations/install.pt
plone/app/relations/interfaces.py
plone/app/relations/local_role.py
plone/app/relations/source.py
plone/app/relations/subscribers.py
plone/app/relations/target.py
plone/app/relations/tests.py
plone/app/relations/userrelations.py
plone/app/relations/userrelations.txt
plone/app/relations/utils.py
plone/app/relations/workflow.py
plone/app/relations/profiles/default/import_steps.xml
plone/app/relations/profiles/default/install_relations.txt