Metadata-Version: 1.0
Name: plone.app.relations
Version: 2.0
Summary: A set of components to provide a content centric API for the engine from plone.relations, as well as a few different core relationship types and policies.
Home-page: http://pypi.python.org/pypi/plone.app.relations
Author: Plone Foundation
Author-email: plone-developers@lists.sourceforge.net
License: GPL version 2
Keywords: relationships references plone
Platform: UNKNOWN
Classifier: Framework :: Plone
Classifier: License :: OSI Approved :: GNU General Public License (GPL)
Classifier: Programming Language :: Python
